[
  {
    "num":"공지",
    "title":"KCC 발코니 이중창(1)",
    "writer":"관리자",
    "date":"2023-09-22",
    "search":"273"
  },
  {
    "num":"공지",
    "title":"KCC 발코니 이중창(2)",
    "writer":"관리자",
    "date":"2023-09-22",
    "search":"273"
  },
  {
    "num":"공지",
    "title":"KCC 발코니 이중창(3)",
    "writer":"관리자",
    "date":"2023-09-22",
    "search":"273"
  },
  {
    "num":"공지",
    "title":"KCC 발코니 이중창(4)",
    "writer":"관리자",
    "date":"2023-09-22",
    "search":"273"
  },
  {
    "num":"1",
    "title":"달해기업 시공은 무엇이 다를까?",
    "writer":"관리자",
    "date":"2023-09-22",
    "search":"5000"
  }

]